valley/__init__.py
valley/declarative.py
valley/exceptions.py
valley/properties.py
valley/schema.py
valley/tests/__init__.py
valley/tests/examples/__init__.py
valley/tests/examples/example_schemas.py
valley/tests/test_declarative.py
valley/tests/test_schema.py
valley/tests/test_utils.py
valley/tests/test_validators.py
valley/utils/__init__.py
valley/utils/imports.py
valley/utils/json_utils.py
valley/validators.py
valley-1.6.dist-info/LICENSE
valley-1.6.dist-info/METADATA
valley-1.6.dist-info/WHEEL
valley-1.6.dist-info/RECORD
