Metadata-Version: 2.1
Name: valley
Version: 1.6
Summary: Python extensible schema validations and declarative syntax helpers.
Home-page: https://github.com/capless/valley
License: Apache-2.0
Keywords: validations,schema,declarative
Author: Brian Jinwright
Requires-Python: >=3.7,<4.0
Classifier: Environment :: Web Environment
Classifier: License :: OSI Approved :: Apache Software License
Classifier: Programming Language :: Python
Classifier: Programming Language :: Python :: 3
Classifier: Programming Language :: Python :: 3.7
Classifier: Programming Language :: Python :: 3.8
Classifier: Programming Language :: Python :: 3.9
Classifier: Programming Language :: Python :: 3.10
Classifier: Programming Language :: Python :: 3.11
Classifier: Programming Language :: Python :: 3.12
Classifier: Topic :: Software Development :: Libraries :: Python Modules
Requires-Dist: envs (>=1.4,<2.0)
Project-URL: Repository, https://github.com/capless/valley
